hvitserk/__init__.py
hvitserk/helpers.py
hvitserk/ai/__init__.py
hvitserk/ai/labeler.py
hvitserk/ai/langchain.py
hvitserk/ai/summarize.py
hvitserk/ai/tyran.py
hvitserk/api/__init__.py
hvitserk/api/app.py
hvitserk/api/client.py
hvitserk/api/issue.py
hvitserk/api/label.py
hvitserk/api/milestone.py
hvitserk/api/pull_request.py
hvitserk/api/repository.py
hvitserk/api/statistics.py
hvitserk/api/webhook.py
hvitserk/config/__init__.py
hvitserk/config/config_parser.py
hvitserk/config/local_config_reader.py
hvitserk/config/remote_config_reader.py
hvitserk/config/v1/__init__.py
hvitserk/config/v1/configs.py
hvitserk/exception/__init__.py
hvitserk/exception/api_error.py
hvitserk/exception/not_found.py
hvitserk/plugins/__init__.py
hvitserk/plugins/v1/__init__.py
hvitserk/plugins/v1/auto_close_pr.py
hvitserk/plugins/v1/auto_triage.py
hvitserk/plugins/v1/labels.py
hvitserk/plugins/v1/stale.py
hvitserk/plugins/v2/__init__.py
hvitserk/util/__init__.py
hvitserk/util/file_system.py
hvitserk/util/logger.py
hvitserk-0.1.2.dist-info/LICENSE.txt
hvitserk-0.1.2.dist-info/METADATA
hvitserk-0.1.2.dist-info/WHEEL
hvitserk-0.1.2.dist-info/top_level.txt
hvitserk-0.1.2.dist-info/RECORD
