Metadata-Version: 2.2
Name: hvitserk
Version: 0.1.2
Summary: Github Automation Package in Python Powered By AI
Home-page: https://github.com/devropen/hvitserk/
Author: Clivern
Author-email: hello@clivern.com
License: MIT
Project-URL: Documentation, https://github.com/devropen/hvitserk/
Project-URL: Source, https://github.com/devropen/hvitserk/
Project-URL: Changelog, https://github.com/devropen/hvitserk/blob/main/CHANGELOG.rst
Project-URL: Tracker, https://github.com/devropen/hvitserk/issues
Project-URL: Download, https://pypi.org/project/hvitserk/#files
Platform: any
Classifier: Development Status :: 5 - Production/Stable
Classifier: Programming Language :: Python
Classifier: License :: OSI Approved :: MIT License
License-File: LICENSE.txt
Requires-Dist: PyGithub<=2.5.0
Requires-Dist: langchain<=0.3.14
Requires-Dist: langchain-openai<=0.2.14
Requires-Dist: pyjwt<=2.10.1
Requires-Dist: cryptography<=44.0.0
Requires-Dist: pycryptodome<=3.21.0
Requires-Dist: python-dateutil<=2.9.0.post0
Requires-Dist: pyyaml<=6.0.2
Requires-Dist: openai<=1.59.6
Requires-Dist: requests<=2.32.3
Requires-Dist: importlib-metadata; python_version < "3.8"
